mac_remote/__init__.py
mac_remote/getmac_linux_fix.py
mac_remote/ping.py
mac_remote_command-0.1.0.dist-info/LICENSE
mac_remote_command-0.1.0.dist-info/METADATA
mac_remote_command-0.1.0.dist-info/WHEEL
mac_remote_command-0.1.0.dist-info/top_level.txt
mac_remote_command-0.1.0.dist-info/RECORD
