Metadata-Version: 2.1
Name: mac-remote-command
Version: 0.1.0
Summary: Client for embedded systems to facilitate remote configuration.
Home-page: https://github.com/FlantasticDan/mac-remote-command
Author: Daniel Flanagan
License: UNKNOWN
Project-URL: Bug Tracker, https://github.com/FlantasticDan/mac-remote-command/issues
Platform: UNKNOWN
Classifier: Programming Language :: Python :: 3
Classifier: License :: OSI Approved :: MIT License
Classifier: Operating System :: OS Independent
Classifier: Development Status :: 3 - Alpha
Requires-Python: >=3.9
License-File: LICENSE
Requires-Dist: httpx
Requires-Dist: getmac
Provides-Extra: oled
Requires-Dist: oled-status ; extra == 'oled'
